{
  "name": "Hallie West",
  "age": 34,
  "address": {
    "street": "Akinu Point",
    "city": "Wepiduc",
    "state": "DC",
    "zip": "21172"
  },
  "contact": {
    "phone": "(664) 587-9002",
    "servicePhone": "800198542"
  },
  "birthday": "1995-07-07T03:52:22.259Z",
  "ip": "99.219.197.106",
  "foo": "bar",
  "profile": {
    "about": "Ke ilpec je wo ileturna zebzozo mituza pumuziz zemciere hudsep ifokhus ducda or fahe ga ti bouwoga. Meoh egizin gutziud letmol az mufut fuhisif po uhi beluz nonemfiv tuwnev gevo ve. Ganibci mejo dawmeul citicez muf zakpule ril fuk wopku awvizde zalise dozif ujras goppiipi ta. Soto li mokuta ijmehuh jur is fo givrikuw vezfab cebe matvacci lu ipi iruaru oci li. Bizsip oh ewetuc limce lufcecbo vurilir redtupot elalugre wahon ral siw tik epi upgo mesare. Fog ta tijoma ipdif wikhiuc obhoiji nahduc tiholpu su zope mag muv ac sikzehvi.",
    "bio": "Ruhze ra we subja losutiwi wegcoclit tucoegi el zuh olredel ikum cestause wibvaeci ruwna piz izawe. Ago obi afacewo vufotoiw ki zu ape rudivse wiv ocrubo sodafotu pak engos ce kizial koma. Doj cosdilu zer lewroowe ujisodil ninnac magehret mizkel ude mifiva nusudisir ine otkeaja ujuhacub."
  },
  "apiKey": "81e93859fec93e0bf93aa792dda5df2058f95cb54be5a0a232b6c5d4d2239db6",
  "currency": {
    "code": "USD",
    "name": "United States Dollar"
  }
}