{
  "name": "Bertha Sherman",
  "age": 27,
  "address": {
    "street": "Cofwi Boulevard",
    "city": "Akogomud",
    "state": "OK",
    "zip": "92888"
  },
  "contact": {
    "phone": "(516) 573-2892",
    "servicePhone": "800946959"
  },
  "birthday": "1990-05-25T05:43:11.536Z",
  "ip": "38.137.168.18",
  "foo": "bar",
  "profile": {
    "about": "Nirze jilfuhal nodud lor re murku kozu uvnaciv tepugo ga jamtig odomu uwno re vu. Uk zahhomi ohopi ze du newgebwu vadures nepsek hile ja lufwihlob ipaedu puves bu ih bog. Ri reonbaf zawu ujgim lis penac ifope gohni galnor ejuducalu jifejri lug weso hafuwom culfaza hegbezid mudaika.",
    "bio": "Sare cebuko zursobu jiriskop jeddo anusi vifu pa bujwi ewi hik cek nahojiaja. Hacecak to saluaji ciwid bi dumufoja noni vuaz zu pebwa pum puh wauje aluti ca heluh leg ci. Pileg nad be wosuvjo kecaz fo munha oc vanevad cuhuhju igdupwo fe cin."
  },
  "apiKey": "7c8fd356d9703ddf8142d94d3f4ff426e99841c34154c1b764af91c8fd0f485e",
  "currency": {
    "code": "EGP",
    "name": "Egypt Pound"
  }
}