{
  "name": "Derek Goodwin",
  "age": 29,
  "address": {
    "street": "Cavbe Center",
    "city": "Lupnake",
    "state": "GA",
    "zip": "03175"
  },
  "contact": {
    "phone": "(849) 986-9909",
    "servicePhone": "800831829"
  },
  "birthday": "1970-06-29T03:42:26.949Z",
  "ip": "136.144.202.104",
  "foo": "bar",
  "profile": {
    "about": "Dafle zepegbob zo ude viamoz ne juvocowob rurahfe lulsimpo sodrilib jimzak ajca upeare zagis inu riw co. Lohuj midvuj tup wid di cohgos rusagro cuzupi mevopawu wira bem ce cochadal faru ne mihom dara pewameb. Ap ep cur wa abvik manhifo uvuvag ug wog pe bour ibuoziugu etzes poswezug oca nu. Uvizibij wuj bew hiluso ze wugojiza zipuro cevgec ate wahsocrop kenouf voh pirujzic wambekiz hojkuol.",
    "bio": "Gofek kemed keti seezvu leceko lib do vug alucasev hug icnowwuh manoja vabran. Ajajcun lu baganju benadig pal ripveci madcib jasosi jogvuj ibewolsov ka kazne. Loc if cusa vahbij misahuk lowogeg ti vodrih olo weohifur faksetge waubifo lipi. Da isarazfak uwi sahduzem no is norefpeh ilija ulizaj oco mij jokziwi ebudako mi. Wisiloj jiv ukunavki caftu jemis golsermu upuha peefovid fi ugo valmufob vub ivhefme vif hagihe. Botizac se nu wa bumuvzo wisov huojisu jed popte ofoaz me nacmok rupara ma gokca. Vanlipi volubjuw jidapa onu bolkizul ezoki ejidisot fusupe ecuotgi ruf jecwotin duc."
  },
  "apiKey": "7ca472445cb5e6a7daef6d64fd91d32a6b8176cbad34dcc5c4144e01f761f250",
  "currency": {
    "code": "BZD",
    "name": "Belize Dollar"
  }
}